{
  "generated_at": "2025-12-02T03:14:45.460101",
  "total_repos": 22,
  "active_repos": 22,
  "archived_repos": 0,
  "total_stars": 0,
  "total_forks": 0,
  "total_contributors": 23,
  "avg_stars": 0.0,
  "avg_forks": 0.0,
  "languages": {
    "Python": 6,
    "TeX": 5,
    "HTML": 4,
    "Jupyter Notebook": 2,
    "JavaScript": 1
  },
  "topics": {
    "finance": 3,
    "machine-learning": 1,
    "portfolio-optimization": 1,
    "reinforcement-learning": 1,
    "credit-risk": 1,
    "explainable-ai": 1,
    "neural-networks": 1,
    "high-frequency-trading": 1,
    "market-microstructure": 1,
    "time-series": 1
  },
  "licenses": {
    "No License": 20,
    "MIT License": 2
  },
  "recent_repos": [
    {
      "name": "ai-in-finance",
      "pushed_at": "2025-12-01T23:20:29+00:00"
    },
    {
      "name": "digital-ai-in-finance",
      "pushed_at": "2025-12-01T23:09:05+00:00"
    },
    {
      "name": "msca-digital-finance",
      "pushed_at": "2025-12-01T23:03:05+00:00"
    },
    {
      "name": "network-based-credit-risk-models",
      "pushed_at": "2025-12-01T23:02:46+00:00"
    },
    {
      "name": "neural-networks-introduction",
      "pushed_at": "2025-12-01T22:56:20+00:00"
    },
    {
      "name": "neural-networks",
      "pushed_at": "2025-12-01T22:45:19+00:00"
    },
    {
      "name": "book-next-word-prediction",
      "pushed_at": "2025-12-01T22:40:20+00:00"
    },
    {
      "name": "Narrative-Digital-Finance",
      "pushed_at": "2025-12-01T22:19:20+00:00"
    },
    {
      "name": "Anomaly_and_Fraud_Detection_in_Blockchain_Networks",
      "pushed_at": "2025-12-01T22:18:06+00:00"
    },
    {
      "name": "Natural-Language-Processing",
      "pushed_at": "2025-12-01T09:59:13+00:00"
    }
  ],
  "popular_repos": [
    {
      "name": "org-dashboard",
      "stars": 0
    },
    {
      "name": "portfolio-optimization-ml",
      "stars": 0
    },
    {
      "name": "credit-risk-prediction",
      "stars": 0
    },
    {
      "name": "market-microstructure",
      "stars": 0
    },
    {
      "name": "Green-Finance",
      "stars": 0
    },
    {
      "name": "Natural-Language-Processing",
      "stars": 0
    },
    {
      "name": "neural-networks",
      "stars": 0
    },
    {
      "name": "ShareBuybacks",
      "stars": 0
    },
    {
      "name": "quantlet-branding-tools",
      "stars": 0
    },
    {
      "name": "demo-repository",
      "stars": 0
    }
  ],
  "repos_without_readme": [
    "neural-networks",
    "ShareBuybacks",
    "neural-networks-introduction",
    "Anomaly_and_Fraud_Detection_in_Blockchain_Networks"
  ],
  "research": {
    "repos_with_papers": 4,
    "repos_with_notebooks": 3,
    "repos_with_datasets": 13,
    "total_publications": 8,
    "total_notebooks": 77
  }
}